mtwaffle/__init__.py
mtwaffle/edi.py
mtwaffle/graphs.py
mtwaffle/mt.py
mtwaffle/mtsite.py
mtwaffle/rfviewer.py
mtwaffle/utils.py
mtwaffle-0.7.dist-info/LICENSE
mtwaffle-0.7.dist-info/METADATA
mtwaffle-0.7.dist-info/WHEEL
mtwaffle-0.7.dist-info/top_level.txt
mtwaffle-0.7.dist-info/RECORD
